undoom_uninstaller_mcp/__init__.py
undoom_uninstaller_mcp/config.py
undoom_uninstaller_mcp/program_manager.py
undoom_uninstaller_mcp/report_generator.py
undoom_uninstaller_mcp/server.py
undoom_uninstaller_mcp/utils.py
undoom_uninstaller_mcp-0.1.7.dist-info/METADATA
undoom_uninstaller_mcp-0.1.7.dist-info/WHEEL
undoom_uninstaller_mcp-0.1.7.dist-info/entry_points.txt
undoom_uninstaller_mcp-0.1.7.dist-info/licenses/LICENSE
undoom_uninstaller_mcp-0.1.7.dist-info/RECORD
