Metadata-Version: 2.4
Name: undoom-uninstaller-mcp
Version: 0.1.7
Summary: A Windows program uninstaller MCP server with advanced management and cleanup features
Project-URL: Homepage, https://github.com/undoom/undoom-uninstaller-mcp
Project-URL: Repository, https://github.com/undoom/undoom-uninstaller-mcp
Project-URL: Issues, https://github.com/undoom/undoom-uninstaller-mcp/issues
Author-email: Undoom <kaikaihuhu666@163.com>
License: MIT
License-File: LICENSE
Keywords: cleanup,mcp,program-management,uninstaller,windows
Classifier: Development Status :: 4 - Beta
Classifier: Intended Audience :: Developers
Classifier: License :: OSI Approved :: MIT License
Classifier: Operating System :: Microsoft :: Windows
Classifier: Programming Language :: Python :: 3
Classifier: Programming Language :: Python :: 3.10
Classifier: Programming Language :: Python :: 3.11
Classifier: Programming Language :: Python :: 3.12
Classifier: Programming Language :: Python :: 3.13
Classifier: Topic :: System :: Systems Administration
Classifier: Topic :: Utilities
Requires-Python: >=3.10
Requires-Dist: mcp>=1.0.0
